<rom base="A2L">
	<romid>
		<xmlid>CF020</xmlid>
		<caseid>5ZVSVNJ</caseid>
		<internalidaddress>A152</internalidaddress>
		<internalidstring>CF020</internalidstring>
		<ecuid>1CF020</ecuid>
		<year>Unknown</year>
		<market>Unknown</market>
		<make>Nissan</make>
		<model>350Z</model>
		<submodel>Unknown</submodel>
		<transmission>Unknown</transmission>
		<memmodel>SH7058</memmodel>
		<endian>Big</endian>
		<flashmethod>Nisprog</flashmethod>
		<filesize>1024kb</filesize>
		<author>Pytrex</author>
		<version>EXPERIMENTAL</version>
	</romid>

	<checksum type="alt" start="0x1408" end="0x313E" sumloc="0x1400" xorloc="0x1404"/>
	<checksum type="std" start="0" end="0xFFFFF" sumloc="0x7B58" xorloc="0x7B50"/>
</rom>
